LICENSE.txt
README.md
setup.py
tokeninfo/__init__.py
tokens.egg-info/PKG-INFO
tokens.egg-info/SOURCES.txt
tokens.egg-info/dependency_links.txt
tokens.egg-info/entry_points.txt
tokens.egg-info/top_level.txt