Metadata-Version: 1.1
Name: tokens
Version: 0.0.2
Summary: tokens is a Python Package created for simply scraping discord account data with the use of an account token.
Home-page: https://github.com/7uk/discord-tokens-package
Author: 7uk
Author-email: doopycheats@gmail.com
License: MIT
Keywords: discord
Platform: UNKNOWN
Classifier: Development Status :: 5 - Production/Stable
Classifier: Intended Audience :: Education
Classifier: Operating System :: Microsoft :: Windows :: Windows 10
Classifier: License :: OSI Approved :: MIT License
Classifier: Programming Language :: Python :: 3
